laz/__init__.py
laz/cli/__init__.py
laz/cli/parser.py
laz/cli/root.py
laz/cli/subcommands/__init__.py
laz/cli/subcommands/help.py
laz/cli/subcommands/init.py
laz/cli/subcommands/show.py
laz/cli/subcommands/tree.py
laz/cli/subcommands/version.py
laz/internal/__init__.py
laz/internal/meta.py
laz/main.py
laz/model/__init__.py
laz/model/act.py
laz/model/action.py
laz/model/base.py
laz/model/configuration.py
laz/model/hook.py
laz/model/matcher.py
laz/model/node.py
laz/model/path.py
laz/model/resolver.py
laz/model/runner.py
laz/model/serializable.py
laz/model/stackable.py
laz/model/target.py
laz/plugins/__init__.py
laz/plugins/alias.py
laz/plugins/aws.py
laz/plugins/groups.py
laz/plugins/jinja.py
laz/plugins/plugin.py
laz/plugins/terraform.py
laz/utils/__init__.py
laz/utils/conf.py
laz/utils/contexts.py
laz/utils/dump.py
laz/utils/errors.py
laz/utils/funcs.py
laz/utils/iterator.py
laz/utils/load.py
laz/utils/logging.py
laz/utils/merge.py
laz/utils/node.py
laz/utils/prodict.py
laz/utils/types.py
laz/utils/utils.py
laz/utils/walk.py
laz-0.0.1a24.dist-info/entry_points.txt
laz-0.0.1a24.dist-info/LICENSE
laz-0.0.1a24.dist-info/WHEEL
laz-0.0.1a24.dist-info/METADATA
laz-0.0.1a24.dist-info/RECORD
