Metadata-Version: 2.1
Name: laz
Version: 0.0.1a24
Summary: CLI tool to configure and run parameterized actions against targets.
Author: Josh Wycuff
Author-email: Josh.Wycuff@gmail.com
Requires-Python: >=3.8,<4
Classifier: Programming Language :: Python :: 3
Classifier: Programming Language :: Python :: 3.8
Classifier: Programming Language :: Python :: 3.9
Classifier: Programming Language :: Python :: 3.10
Requires-Dist: Jinja2 (>=3,<4)
Requires-Dist: PyYAML (>=6,<7)
Requires-Dist: boto3[aws]
Requires-Dist: braceexpand (>=0.1,<1)
Requires-Dist: prodict (>=0.8,<1)
